jumpstarter_all/noop_test.py
jumpstarter_all-0.7.4.dist-info/METADATA
jumpstarter_all-0.7.4.dist-info/WHEEL
jumpstarter_all-0.7.4.dist-info/RECORD
