Metadata-Version: 2.4
Name: jumpstarter-all
Version: 0.7.4
Summary: Jumpstarter meta-package which will install all packages
Project-URL: Homepage, https://jumpstarter.dev
Project-URL: source_archive, https://github.com/jumpstarter-dev/repo/archive/c5d38de69eadbb8eb0388bcfe3430a679fff0059.zip
Author-email: Miguel Angel Ajo <majopela@redhat.com>
License-Expression: Apache-2.0
Requires-Python: >=3.11
Requires-Dist: jumpstarter-cli-admin==0.7.4
Requires-Dist: jumpstarter-cli-common==0.7.4
Requires-Dist: jumpstarter-cli-driver==0.7.4
Requires-Dist: jumpstarter-cli==0.7.4
Requires-Dist: jumpstarter-driver-can==0.7.4
Requires-Dist: jumpstarter-driver-composite==0.7.4
Requires-Dist: jumpstarter-driver-corellium==0.7.4
Requires-Dist: jumpstarter-driver-dutlink==0.7.4
Requires-Dist: jumpstarter-driver-flashers==0.7.4
Requires-Dist: jumpstarter-driver-gpiod==0.7.4
Requires-Dist: jumpstarter-driver-http==0.7.4
Requires-Dist: jumpstarter-driver-network==0.7.4
Requires-Dist: jumpstarter-driver-opendal==0.7.4
Requires-Dist: jumpstarter-driver-power==0.7.4
Requires-Dist: jumpstarter-driver-probe-rs==0.7.4
Requires-Dist: jumpstarter-driver-pyserial==0.7.4
Requires-Dist: jumpstarter-driver-qemu==0.7.4
Requires-Dist: jumpstarter-driver-ridesx==0.7.4
Requires-Dist: jumpstarter-driver-sdwire==0.7.4
Requires-Dist: jumpstarter-driver-shell==0.7.4
Requires-Dist: jumpstarter-driver-snmp==0.7.4
Requires-Dist: jumpstarter-driver-ssh==0.7.4
Requires-Dist: jumpstarter-driver-tftp==0.7.4
Requires-Dist: jumpstarter-driver-tmt==0.7.4
Requires-Dist: jumpstarter-driver-uboot==0.7.4
Requires-Dist: jumpstarter-driver-ustreamer==0.7.4
Requires-Dist: jumpstarter-driver-yepkit==0.7.4
Requires-Dist: jumpstarter-imagehash==0.7.4
Requires-Dist: jumpstarter-kubernetes==0.7.4
Requires-Dist: jumpstarter-protocol==0.7.4
Requires-Dist: jumpstarter-testing==0.7.4
Requires-Dist: jumpstarter==0.7.4
